[
  {
    "pos": "1",
    "seed": "1",
    "school": "Kansas"
  },
  {
    "pos": "2",
    "seed":"16",
    "school": "Austin Peay"
  },
  {
    "pos": "3",
    "seed": "8",
    "school": "Colorado"
  },
  {
    "pos": "4",
    "seed": "9",
    "school": "Connecticut"
  },
  {
    "pos": "5",
    "seed": "5",
    "school": "Maryland"
  },
  {
    "pos": "6",
    "seed": "12",
    "school": "South Dakota St."
  },
  {
    "pos": "7",
    "seed": "4",
    "school": "California"
  },
  {
    "pos": "8",
    "seed": "13",
    "school": "Hawaii"
  },
  {
    "pos": "9",
    "seed":"6",
    "school": "Arizona"
  },
  {
    "pos": "10a",
    "seed": "11",
    "school": "Vanderbilt"
  },
  {
    "pos": "10b",
    "seed": "11",
    "school": "Wichita St."
  },
  {
    "pos": "11",
    "seed": "3",
    "school": "Miami FL"
  },
  {
    "pos": "12",
    "seed": "14",
    "school": "Buffalo"
  },
  {
    "pos": "13",
    "seed": "7",
    "school": "Iowa"
  },
  {
    "pos": "14",
    "seed": "10",
    "school": "Temple"
  },
  {
    "pos": "15",
    "seed": "2",
    "school": "Villanova"
  },
  {
    "pos": "16",
    "seed": "15",
    "school": "UNC Asheville"
  },
  {
    "pos": "17",
    "seed": "1",
    "school": "Oregon"
  },
  {
    "pos": "18a",
    "seed": "16",
    "school": "Holy Cross"
  },
  {
    "pos": "18b",
    "seed": "16",
    "school": "Southern"
  },
  {
    "pos": "19",
    "seed": "8",
    "school": "Saint Joseph's"
  },
  {
    "pos": "20",
    "seed": "9",
    "school": "Cincinnati"
  },
  {
    "pos": "21",
    "seed": "5",
    "school": "Baylor"
  },
  {
    "pos": "22",
    "seed": "12",
    "school": "Yale"
  },
  {
    "pos": "23",
    "seed": "4",
    "school": "Duke"
  },
  {
    "pos": "24",
    "seed": "13",
    "school": "UNC Wilmington"
  },
  {
    "pos": "25",
    "seed": "6",
    "school": "Texas"
  },
  {
    "pos": "26",
    "seed": "11",
    "school": "Northern Iowa"
  },
  {
    "pos": "27",
    "seed": "3",
    "school": "Texas A&M"
  },
  {
    "pos": "28",
    "seed": "14",
    "school": "Green Bay"
  },
  {
    "pos": "29",
    "seed": "7",
    "school": "Oregon St."
  },
  {
    "pos": "30",
    "seed": "10",
    "school": "VCU"
  },
  {
    "pos": "31",
    "seed": "2",
    "school": "Oklahoma"
  },
  {
    "pos": "32",
    "seed": "15",
    "school": "Cal St. Bakersfield"
  },
  {
    "pos": "33",
    "seed": "1",
    "school": "North Carolina"
  },
  {
    "pos": "34a",
    "seed": "16",
    "school": "Florida Gulf Coast"
  },
  {
    "pos": "34b",
    "seed": "16",
    "school": "Fairleigh Dickinson"
  },
  {
    "pos": "35",
    "seed": "8",
    "school": "USC"
  },
  {
    "pos": "36",
    "seed": "9",
    "school": "Providence"
  },
  {
    "pos": "37",
    "seed": "5",
    "school": "Indiana"
  },
  {
    "pos": "38",
    "seed": "12",
    "school": "Chattanooga"
  },
  {
    "pos": "39",
    "seed": "4",
    "school": "Kentucky"
  },
  {
    "pos": "40",
    "seed": "13",
    "school": "Stony Brook"
  },
  {
    "pos": "41",
    "seed": "6",
    "school": "Notre Dame"
  },
  {
    "pos": "42a",
    "seed": "11",
    "school": "Michigan"
  },
  {
    "pos": "42b",
    "seed": "11",
    "school": "Tulsa"
  },
  {
    "pos": "43",
    "seed": "3",
    "school": "West Virginia"
  },
  {
    "pos": "44",
    "seed": "14",
    "school": "Stephen F. Austin"
  },
  {
    "pos": "45",
    "seed": "7",
    "school": "Wisconsin"
  },
  {
    "pos": "46",
    "seed": "10",
    "school": "Pittsburgh"
  },
  {
    "pos": "47",
    "seed": "2",
    "school": "Xavier"
  },
  {
    "pos": "48",
    "seed": "15",
    "school": "Weber St."
  },
  {
    "pos": "49",
    "seed": "1",
    "school": "Virginia"
  },
  {
    "pos": "50",
    "seed": "16",
    "school": "Hampton"
  },
  {
    "pos": "51",
    "seed": "8",
    "school": "Texas Tech"
  },
  {
    "pos": "52",
    "seed": "9",
    "school": "Butler"
  },
  {
    "pos": "53",
    "seed": "5",
    "school": "Purdue"
  },
  {
    "pos": "54",
    "seed": "12",
    "school": "Arkansas Little Rock"
  },
  {
    "pos": "55",
    "seed": "4",
    "school": "Iowa St."
  },
  {
    "pos": "56",
    "seed": "13",
    "school": "Iona"
  },
  {
    "pos": "57",
    "seed": "6",
    "school": "Seton Hall"
  },
  {
    "pos": "58",
    "seed": "11",
    "school": "Gonzaga"
  },
  {
    "pos": "59",
    "seed": "3",
    "school": "Utah"
  },
  {
    "pos": "60",
    "seed": "14",
    "school": "Fresno St."
  },
  {
    "pos": "61",
    "seed": "7",
    "school": "Dayton"
  },
  {
    "pos": "62",
    "seed": "10",
    "school": "Syracuse"
  },
  {
    "pos": "63",
    "seed": "2",
    "school": "Michigan St."
  },
  {
    "pos": "64",
    "seed": "15",
    "school": "Middle Tennessee"
  }
]
